{
  "projects": [
    {
      "name": "Teste",
      "budget": "1000",
      "category": {
        "id": "2",
        "name": "Desenvolvimento"
      },
      "cost": 500,
      "services": [
        {
          "name": "teste",
          "cost": "500",
          "description": "teste",
          "id": "a45f8fb6-3253-4985-9541-2ed72be79e68"
        }
      ],
      "id": 1
    }
  ],
  "categorias": [
    {
      "id": 1,
      "name": "infra"
    },
    {
      "id": 2,
      "name": "Desenvolvimento"
    },
    {
      "id": 3,
      "name": "Design"
    },
    {
      "id": 4,
      "name": "Planejamento"
    }
  ]
}